LICENSE.rst
README.rst
setup.cfg
setup.py
PyHDFS.egg-info/PKG-INFO
PyHDFS.egg-info/SOURCES.txt
PyHDFS.egg-info/dependency_links.txt
PyHDFS.egg-info/requires.txt
PyHDFS.egg-info/top_level.txt
pyhdfs/__init__.py
pyhdfs/py.typed