Metadata-Version: 2.4
Name: PyHDFS
Version: 0.4.0
Summary: Pure Python HDFS client
Home-page: https://github.com/jingw/pyhdfs
Author: Jing Wang
Author-email: 99jingw@gmail.com
License: MIT License
Classifier: Intended Audience :: Developers
Classifier: License :: OSI Approved :: MIT License
Classifier: Operating System :: OS Independent
Classifier: Programming Language :: Python
Classifier: Programming Language :: Python :: 3
Classifier: Programming Language :: Python :: 3 :: Only
Classifier: Topic :: System :: Filesystems
Requires-Python: >=3.9
License-File: LICENSE.rst
Requires-Dist: requests
Dynamic: license-file
